LICENSE
MANIFEST.in
README.rst
setup.cfg
setup.py
scirate/__init__.py
scirate/author.py
scirate/category.py
scirate/client.py
scirate/paper.py
scirate/parser.py
scirate/request.py
scirate/util.py
scirate.egg-info/PKG-INFO
scirate.egg-info/SOURCES.txt
scirate.egg-info/dependency_links.txt
scirate.egg-info/requires.txt
scirate.egg-info/top_level.txt