Metadata-Version: 1.1
Name: scirate
Version: 0.0.8
Summary: Python wrapper for extracting content from Scirate.
Home-page: https://github.com/vprusso/scirate
Author: Vincent Russo
Author-email: vincentrusso1@gmail.com
License: MIT
Project-URL: Homepage, http://vprusso.github.io/
Keywords: scirate,scirate API,scirate python
Platform: UNKNOWN
Classifier: Development Status :: 4 - Beta
Classifier: Intended Audience :: Developers
Classifier: License :: OSI Approved :: MIT License
Classifier: Natural Language :: English
Classifier: Programming Language :: Python :: 2.7
Classifier: Programming Language :: Python :: 3.5
